falcon_api_browse/__init__.py
falcon_api_browse/middleware.py
falcon_api_browse/templates/base.html
falcon_api_browse/views.py
falcon_api_browse-0.1.1.dist-info/LICENSE
falcon_api_browse-0.1.1.dist-info/METADATA
falcon_api_browse-0.1.1.dist-info/WHEEL
falcon_api_browse-0.1.1.dist-info/RECORD
