Metadata-Version: 2.1
Name: falcon-api-browse
Version: 0.1.1
Summary: Middleware for Falcon web framework to browse JSON API in HTML
Home-page: https://github.com/maxking/falcon-api-browse
License: Apache-2.0
Keywords: falcon
Author: Abhilash Raj
Author-email: raj.abhilash1@gmail.com
Requires-Python: >=3.7
Classifier: License :: OSI Approved :: Apache Software License
Classifier: Programming Language :: Python :: 3
Classifier: Programming Language :: Python :: 3.7
Classifier: Programming Language :: Python :: 3.8
Classifier: Programming Language :: Python :: 3.9
Classifier: Programming Language :: Python :: 3.10
Classifier: Programming Language :: Python :: 3.11
Requires-Dist: Jinja2 (>=2.0.0)
Requires-Dist: falcon (>=3.0.0)
Requires-Dist: importlib-resources (>=5.4.0,<6.0.0)
Project-URL: Repository, https://github.com/maxking/falcon-api-browse
